hw5lib/__init__.py
hw5lib/myfuncs.py
hw5lib-1.0.1.dist-info/LICENSE.txt
hw5lib-1.0.1.dist-info/METADATA
hw5lib-1.0.1.dist-info/WHEEL
hw5lib-1.0.1.dist-info/top_level.txt
hw5lib-1.0.1.dist-info/RECORD
